jdepp_ext.cpython-39-i386-linux-gnu.so
jdepp.libs/libgcc_s-8b50eaaa.so.1
jdepp.libs/libstdc++-8baf04f9.so.6.0.28
jdepp-0.1.8.dist-info/METADATA
jdepp-0.1.8.dist-info/jdepp.BSD
jdepp-0.1.8.dist-info/top_level.txt
jdepp-0.1.8.dist-info/WHEEL
jdepp-0.1.8.dist-info/jdepp.LGPL
jdepp-0.1.8.dist-info/RECORD
jdepp-0.1.8.dist-info/jdepp.GPL
jdepp-0.1.8.dist-info/LICENSE
jdepp-0.1.8.dist-info/entry_points.txt
jdepp/pa.h
jdepp/_version.py
jdepp/python-binding-jdepp.cc
jdepp/kernel.cc
jdepp/linear.h
jdepp/typedef.h
jdepp/classify.cc
jdepp/main.py
jdepp/jdepp_tools.py
jdepp/pdep.h
jdepp/optparse.UNLICENSE
jdepp/io-util.cc
jdepp/timer.cc
jdepp/timer.h
jdepp/classify.h
jdepp/pdep.cc
jdepp/kernel.h
jdepp/io-util.hh
jdepp/cedar.h
jdepp/__init__.py
jdepp/linear.cc
jdepp/pecco.h
jdepp/config.h
jdepp/jdepp.cc
jdepp/optparse.h
