Metadata-Version: 2.1
Name: jdepp
Version: 0.1.8
Summary: Python binding for J.DepP(C++ implementation of Japanese Dependency Parsers)
Home-page: https://github.com/lighttransport/jdepp-python/
Author-email: Syoyo Fujita <syoyo@lighttransport.com>
License-File: LICENSE
License-File: jdepp.BSD
License-File: jdepp.GPL
License-File: jdepp.LGPL
